cltl/dialogue_evaluation/__init__.py
cltl/dialogue_evaluation/add_likelihood_to_emissor.py
cltl/dialogue_evaluation/api.py
cltl/dialogue_evaluation/graph_evaluation.py
cltl/dialogue_evaluation/likelihood_evaluation.py
cltl/dialogue_evaluation/manual_evaluation.py
cltl/dialogue_evaluation/metrics_correlations.py
cltl/dialogue_evaluation/metrics_plotting.py
cltl/dialogue_evaluation/plot_interaction.py
cltl/dialogue_evaluation/reference_evaluation.py
cltl/dialogue_evaluation/statistical_evaluation.py
cltl/dialogue_evaluation/usr_dialogue_retrieval_evaluation.py
cltl/dialogue_evaluation/metrics/__init__.py
cltl/dialogue_evaluation/metrics/brain_measures.py
cltl/dialogue_evaluation/metrics/graph_measures.py
cltl/dialogue_evaluation/metrics/ontology_measures.py
cltl/dialogue_evaluation/metrics/utterance_likelihood.py
cltl/dialogue_evaluation/metrics/utterance_usr_dialog_retrieval.py
cltl/dialogue_evaluation/utils/__init__.py
cltl/dialogue_evaluation/utils/constants.py
cltl/dialogue_evaluation/utils/image_signal.py
cltl/dialogue_evaluation/utils/map_rdf_files.py
cltl/dialogue_evaluation/utils/scenario_check.py
cltl/dialogue_evaluation/utils/text_signal.py
cltl.dialogue_evaluation-0.2.7.dev1.dist-info/LICENSE
cltl.dialogue_evaluation-0.2.7.dev1.dist-info/METADATA
cltl.dialogue_evaluation-0.2.7.dev1.dist-info/WHEEL
cltl.dialogue_evaluation-0.2.7.dev1.dist-info/top_level.txt
cltl.dialogue_evaluation-0.2.7.dev1.dist-info/RECORD
