Metadata-Version: 2.1
Name: cltl.dialogue_evaluation
Version: 0.2.7.dev1
Summary: The Leolani Language module for evaluating interactions
Home-page: https://github.com/leolani/cltl-dialogueevaluation
License: MIT License
Requires-Python: >=3.7
License-File: LICENSE
Requires-Dist: rdflib~=6.1.1
Requires-Dist: networkx~=2.6.3
Requires-Dist: numpy~=1.21.5
Requires-Dist: pandas
Requires-Dist: scipy~=1.7.3
Requires-Dist: seaborn~=0.11.2
Requires-Dist: transformers~=4.19.4
Requires-Dist: emissor~=0.0.dev5
Requires-Dist: torch~=1.11.0
